realtimex_sdk/__init__.py
realtimex_sdk/activities.py
realtimex_sdk/api.py
realtimex_sdk/client.py
realtimex_sdk/llm.py
realtimex_sdk/port.py
realtimex_sdk/task.py
realtimex_sdk/tts.py
realtimex_sdk/webhook.py
realtimex_sdk-1.2.4.dist-info/METADATA
realtimex_sdk-1.2.4.dist-info/WHEEL
realtimex_sdk-1.2.4.dist-info/RECORD
