Metadata-Version: 2.4
Name: realtimex-sdk
Version: 1.2.4
Summary: Python SDK for building Local Apps that integrate with RealtimeX
Project-URL: Homepage, https://github.com/realtimex/rtx-local-app-sdk
Project-URL: Documentation, https://docs.realtimex.ai/local-apps
Project-URL: Repository, https://github.com/realtimex/rtx-local-app-sdk
Author-email: RealtimeX Team <team@realtimex.ai>
License-Expression: MIT
Classifier: Development Status :: 4 - Beta
Classifier: Intended Audience :: Developers
Classifier: License :: OSI Approved :: MIT License
Classifier: Programming Language :: Python :: 3
Classifier: Programming Language :: Python :: 3.8
Classifier: Programming Language :: Python :: 3.9
Classifier: Programming Language :: Python :: 3.10
Classifier: Programming Language :: Python :: 3.11
Classifier: Programming Language :: Python :: 3.12
Requires-Python: >=3.8
Requires-Dist: httpx>=0.25.0
Provides-Extra: dev
Requires-Dist: pytest-asyncio>=0.21.0; extra == 'dev'
Requires-Dist: pytest>=7.0.0; extra == 'dev'
